weglide_client/__init__.py
weglide_client/api_client.py
weglide_client/api_response.py
weglide_client/configuration.py
weglide_client/exceptions.py
weglide_client/py.typed
weglide_client/rest.py
weglide_client/api/__init__.py
weglide_client/api/achievement_api.py
weglide_client/api/aircraft_api.py
weglide_client/api/airport_api.py
weglide_client/api/auth_api.py
weglide_client/api/badge_api.py
weglide_client/api/club_api.py
weglide_client/api/comment_api.py
weglide_client/api/comment_reaction_api.py
weglide_client/api/competition_api.py
weglide_client/api/copilot_api.py
weglide_client/api/declaration_api.py
weglide_client/api/fix_api.py
weglide_client/api/flight_api.py
weglide_client/api/flight_like_api.py
weglide_client/api/flight_star_api.py
weglide_client/api/flightcollection_api.py
weglide_client/api/flightcollection_star_api.py
weglide_client/api/flightdata_api.py
weglide_client/api/flightday_api.py
weglide_client/api/flightdetail_api.py
weglide_client/api/follower_api.py
weglide_client/api/igcfile_api.py
weglide_client/api/notification_api.py
weglide_client/api/push_subscription_api.py
weglide_client/api/ranking_api.py
weglide_client/api/robots_api.py
weglide_client/api/search_api.py
weglide_client/api/segment_api.py
weglide_client/api/segment_star_api.py
weglide_client/api/story_api.py
weglide_client/api/task_api.py
weglide_client/api/task_score_api.py
weglide_client/api/task_star_api.py
weglide_client/api/thermal_api.py
weglide_client/api/travel_api.py
weglide_client/api/user_api.py
weglide_client/api/user_certificate_api.py
weglide_client/api/user_device_api.py
weglide_client/api/user_group_api.py
weglide_client/api/user_group_device_api.py
weglide_client/api/user_message_api.py
weglide_client/api/waypoint_api.py
weglide_client/api/waypointcollection_api.py
weglide_client/models/__init__.py
weglide_client/models/achievement.py
weglide_client/models/achievement_with_badge.py
weglide_client/models/achievement_with_badge_no_user.py
weglide_client-0.1.5.dist-info/licenses/LICENSE
weglide_client-0.1.5.dist-info/METADATA
weglide_client-0.1.5.dist-info/WHEEL
weglide_client-0.1.5.dist-info/top_level.txt
weglide_client-0.1.5.dist-info/RECORD
