Metadata-Version: 2.4
Name: weglide-client
Version: 0.1.5
Summary: Python client for the WeGlide API. WeGlide is an online platform where glider pilots can share and analyze their flights, participate in competitions, and connect with the global gliding community.
Home-page: 
Author: OpenAPI Generator community
Author-email: OpenAPI Generator Community <team@openapitools.org>
License-Expression: MIT
Project-URL: Homepage, https://github.com/develmusa/weglide-python-client
Project-URL: Issues, https://github.com/develmusa/weglide-python-client/issues
Project-URL: WeGlide, https://weglide.org
Project-URL: Documentation, https://docs.weglide.org/creators/developers.html
Classifier: Programming Language :: Python :: 3
Classifier: Operating System :: OS Independent
Requires-Python: >=3.9
License-File: LICENSE
Requires-Dist: urllib3<3.0.0,>=1.25.3
Requires-Dist: python-dateutil>=2.8.2
Requires-Dist: typing-extensions>=4.7.1
Requires-Dist: pydantic>=2.10.6
Dynamic: author
Dynamic: license-file
